.gitattributes
.gitignore
.readthedocs.yml
MANIFEST.in
README.rst
environment.yml
example.py
pyproject.toml
setup.cfg
setup.py
tox.ini
.github/workflows/ci_tests.yml
docs/.DS_Store
docs/Makefile
docs/_kelp_vis.html
docs/_kelp_vis.py
docs/conf.py
docs/index.rst
docs/make.bat
docs/_static/kelp.css
docs/_static/kelp.ico
docs/_static/kelp.png
docs/_static/kelp.svg
docs/kelp/background.rst
docs/kelp/gettingstarted.rst
docs/kelp/index.rst
docs/kelp/installation.rst
docs/kelp/interactive.rst
docs/kelp/kelp_geoviews.html
docs/kelp/kelp_geoviews.py
docs/kelp/optimization.rst
docs/kelp/reflected.rst
kelp/__init__.py
kelp/_astropy_init.py
kelp/conftest.py
kelp/core.py
kelp/fast.c
kelp/fast.pyx
kelp/registries.py
kelp/version.py
kelp.egg-info/PKG-INFO
kelp.egg-info/SOURCES.txt
kelp.egg-info/dependency_links.txt
kelp.egg-info/not-zip-safe
kelp.egg-info/requires.txt
kelp.egg-info/top_level.txt
kelp/data/README.rst
kelp/data/filters.json
kelp/data/kepler_response_hires1.txt
kelp/data/planets.json
kelp/jax/__init__.py
kelp/jax/jax.py
kelp/tests/__init__.py
kelp/tests/test_core.py
kelp/tests/test_jax.py
kelp/tests/test_theano.py
kelp/theano/__init__.py
kelp/theano/theano.py
licenses/LICENSE.rst
licenses/README.rst
licenses/TEMPLATE_LICENCE.rst
notebooks/demo.ipynb