Metadata-Version: 2.1
Name: kelp
Version: 0.5.0
Summary: Photometric phase curves of exoplanets
Home-page: https://github.com/bmorris3/kelp
Author: Brett M. Morris
Author-email: morrisbrettm@gmail.com
License: BSD 3-Clause
Platform: UNKNOWN
Requires-Python: >=3.6
Provides-Extra: test
Provides-Extra: docs
License-File: licenses/LICENSE.rst
